aigyminsper/__init__.py
aigyminsper/search/CSPAlgorithms.py
aigyminsper/search/Graph.py
aigyminsper/search/SearchAlgorithms.py
aigyminsper/search/__init__.py
aigyminsper-0.2.1.dist-info/LICENSE
aigyminsper-0.2.1.dist-info/METADATA
aigyminsper-0.2.1.dist-info/WHEEL
aigyminsper-0.2.1.dist-info/top_level.txt
aigyminsper-0.2.1.dist-info/RECORD
