Metadata-Version: 2.1
Name: aigyminsper
Version: 0.2.1
Summary: A libray that helps you to learn Artificial Intelligence.
Home-page: https://github.com/insper/ai_gym/
Author: Fabricio Barth
Author-email: fabriciojb@insper.edu.br
License-File: LICENSE
